{"status":200,"query":{"country":"AM","year":"2020"},"requestId":"e4ad8da4-3301-4ffe-9440-82ac789f8e36","holidays":[{"id":"20200101_9083e91f24a93b9a55b934a902d28fce","name":"New Year's Day","date":"2020-01-01","observed":"2020-01-01","substitute":false,"start":"2020-01-01T00:00:00Z","end":"2020-01-01T23:59:59Z","type":"public","public":true,"country":"AM","subdivisions":[]},{"id":"20200102_e5234a79aec9eddc84016626df01570e","name":"Second Day of the New Year","date":"2020-01-02","observed":"2020-01-02","substitute":false,"start":"2020-01-02T00:00:00Z","end":"2020-01-02T23:59:59Z","type":"public","public":true,"country":"AM","subdivisions":[]},{"id":"20200103_b2d66c1bd06ab9b58fb7e331262a56a0","name":"Third Day of the New Year","date":"2020-01-03","observed":"2020-01-03","substitute":false,"start":"2020-01-03T00:00:00Z","end":"2020-01-03T23:59:59Z","type":"public","public":true,"country":"AM","subdivisions":[]},{"id":"20200104_bdbd6f322ac6289528d91762308d2dd5","name":"Fourth Day of the New Year","date":"2020-01-04","observed":"2020-01-04","substitute":false,"start":"2020-01-04T00:00:00Z","end":"2020-01-04T23:59:59Z","type":"public","public":true,"country":"AM","subdivisions":[]},{"id":"20200105_e4ad887f7fb2cd860ed30f231c7dce2e","name":"Orthodox Christmas Eve","date":"2020-01-05","observed":"2020-01-05","substitute":false,"start":"2020-01-05T00:00:00Z","end":"2020-01-05T23:59:59Z","type":"public","public":true,"country":"AM","subdivisions":[]},{"id":"20200106_e2033b4d074668deda2370488fbf7ff0","name":"Orthodox Christmas Day","date":"2020-01-06","observed":"2020-01-06","substitute":false,"start":"2020-01-06T00:00:00Z","end":"2020-01-06T23:59:59Z","type":"public","public":true,"country":"AM","subdivisions":[]},{"id":"20200107_ad60bd526942721c1a23770b39e6359f","name":"The Day of Commemoration of All Dead People after Christmas Day","date":"2020-01-07","observed":"2020-01-07","substitute":false,"start":"2020-01-07T00:00:00Z","end":"2020-01-07T23:59:59Z","type":"public","public":true,"country":"AM","subdivisions":[]},{"id":"20200128_09e874d77d1f960201571a73352788dc","name":"Army Day","date":"2020-01-28","observed":"2020-01-28","substitute":false,"start":"2020-01-28T00:00:00Z","end":"2020-01-28T23:59:59Z","type":"public","public":true,"country":"AM","subdivisions":[]},{"id":"20200303_c7ab7f23498f5ff4a4715d50cbded6a4","name":"World Wildlife Day","date":"2020-03-03","observed":"2020-03-03","substitute":false,"start":"2020-03-03T00:00:00Z","end":"2020-03-03T23:59:59Z","type":"observance","public":false,"country":"AM","subdivisions":[]},{"id":"20200308_be88299b986eec64ee405fcfdac79001","name":"International Women's Day","date":"2020-03-08","observed":"2020-03-08","substitute":false,"start":"2020-03-08T00:00:00Z","end":"2020-03-08T23:59:59Z","type":"public","public":true,"country":"AM","subdivisions":[]},{"id":"20200308_e64077fbf9c40729ed122ad150c2e41f","name":"Mother's Day","date":"2020-03-08","observed":"2020-03-08","substitute":false,"start":"2020-03-08T00:00:00Z","end":"2020-03-08T23:59:59Z","type":"observance","public":false,"country":"AM","subdivisions":[]},{"id":"20200320_b2866c9220c0d427d06a23a516d5ef25","name":"March Equinox","date":"2020-03-20","observed":"2020-03-20","substitute":false,"start":"2020-03-20T00:00:00Z","end":"2020-03-20T23:59:59Z","type":"observance","public":false,"country":"AM","subdivisions":[]},{"id":"20200424_7ad180b1a0da6970bdcb1a130b9e787e","name":"Armenian Genocide Remembrance Day","date":"2020-04-24","observed":"2020-04-24","substitute":false,"start":"2020-04-24T00:00:00Z","end":"2020-04-24T23:59:59Z","type":"public","public":true,"country":"AM","subdivisions":[]},{"id":"20200501_23901a552dc86d67e271a63ab3e9edfe","name":"International Workers' Day","date":"2020-05-01","observed":"2020-05-01","substitute":false,"start":"2020-05-01T00:00:00Z","end":"2020-05-01T23:59:59Z","type":"public","public":true,"country":"AM","subdivisions":[]},{"id":"20200509_a382dac388cc1ad86f2c3538d6fdaec3","name":"Victory and Peace Day","date":"2020-05-09","observed":"2020-05-09","substitute":false,"start":"2020-05-09T00:00:00Z","end":"2020-05-09T23:59:59Z","type":"public","public":true,"country":"AM","subdivisions":[]},{"id":"20200528_ab3ca54a913262500304cbf1a24c2a16","name":"Republic Day","date":"2020-05-28","observed":"2020-05-28","substitute":false,"start":"2020-05-28T00:00:00Z","end":"2020-05-28T23:59:59Z","type":"public","public":true,"country":"AM","subdivisions":[]},{"id":"20200620_c7efcc248b22c60e4ab651f2eef23bf3","name":"June Solstice","date":"2020-06-20","observed":"2020-06-20","substitute":false,"start":"2020-06-20T00:00:00Z","end":"2020-06-20T23:59:59Z","type":"observance","public":false,"country":"AM","subdivisions":[]},{"id":"20200630_bf68c72413bed8e8b1bad3bb51c8ad1f","name":"International Asteroid Day","date":"2020-06-30","observed":"2020-06-30","substitute":false,"start":"2020-06-30T00:00:00Z","end":"2020-06-30T23:59:59Z","type":"observance","public":false,"country":"AM","subdivisions":[]},{"id":"20200705_b58c68f95ed1dde2f8db360ec2230bbf","name":"Constitution Day","date":"2020-07-05","observed":"2020-07-05","substitute":false,"start":"2020-07-05T00:00:00Z","end":"2020-07-05T23:59:59Z","type":"public","public":true,"country":"AM","subdivisions":[]},{"id":"20200718_b0c2cc17c7732108764743ab1d7402f8","name":"Nelson Mandela International Day","date":"2020-07-18","observed":"2020-07-18","substitute":false,"start":"2020-07-18T00:00:00Z","end":"2020-07-18T23:59:59Z","type":"observance","public":false,"country":"AM","subdivisions":[]},{"id":"20200921_96c5ba502ec3e5a8ff694efd260490bf","name":"Independence Day","date":"2020-09-21","observed":"2020-09-21","substitute":false,"start":"2020-09-21T00:00:00Z","end":"2020-09-21T23:59:59Z","type":"public","public":true,"country":"AM","subdivisions":[]},{"id":"20200922_6233038933f9b229325b9fc63ed52680","name":"September Equinox","date":"2020-09-22","observed":"2020-09-22","substitute":false,"start":"2020-09-22T00:00:00Z","end":"2020-09-22T23:59:59Z","type":"observance","public":false,"country":"AM","subdivisions":[]},{"id":"20201221_f5aaad45840c5fb3b79bd6e4181d6b30","name":"December Solstice","date":"2020-12-21","observed":"2020-12-21","substitute":false,"start":"2020-12-21T00:00:00Z","end":"2020-12-21T23:59:59Z","type":"observance","public":false,"country":"AM","subdivisions":[]},{"id":"20201231_ab8a18594dab0679d4e96d1eeaba8172","name":"New Year's Eve","date":"2020-12-31","observed":"2020-12-31","substitute":false,"start":"2020-12-31T00:00:00Z","end":"2020-12-31T23:59:59Z","type":"public","public":true,"country":"AM","subdivisions":[]}],"availableFilters":{"language":["af","am","ar","az","be","bg","bn","bs","ca","ceb","co","cs","cy","da","de","el","en","eo","es","et","eu","fa","fi","fr","fy","ga","gd","gl","gu","ha","haw","he","hi","hmn","hr","ht","hu","hy","id","ig","is","it","ja","jw","ka","kk","km","kn","ko","ku","ky","la","lb","lo","lt","lv","mg","mi","mk","ml","mn","mr","ms","mt","my","ne","nl","no","ny","or","pa","pl","ps","pt","ro","ru","rw","sd","si","sk","sl","sm","sn","so","sq","sr","st","su","sv","sw","ta","te","tg","th","tk","tl","tr","tt","ug","uk","ur","uz","vi","xh","yi","yo","zh","zh-TW","zu"]}}