{
    "status": 200,
    "query": {
        "country": "RU",
        "year": "2020"
    },
    "requestId": "ab3c090c-21e1-48f5-9701-3680b65c24b5",
    "holidays": [{
        "id": "20200101_272020371b48dcbc989dcb51a2b0d297",
        "name": "New Year's Day",
        "date": "2020-01-01",
        "observed": "2020-01-01",
        "substitute": false,
        "start": "2020-01-01T00:00:00Z",
        "end": "2020-01-01T23:59:59Z",
        "type": "public",
        "public": true,
        "country": "RU",
        "subdivisions": []
    }, {
        "id": "20200102_42df9fd2d40a9b3eea130eece3af1b9f",
        "name": "Second Day of the New Year",
        "date": "2020-01-02",
        "observed": "2020-01-02",
        "substitute": false,
        "start": "2020-01-02T00:00:00Z",
        "end": "2020-01-02T23:59:59Z",
        "type": "public",
        "public": true,
        "country": "RU",
        "subdivisions": []
    }, {
        "id": "20200103_b995fa09500080850e420015508762cc",
        "name": "Third Day of the New Year",
        "date": "2020-01-03",
        "observed": "2020-01-03",
        "substitute": false,
        "start": "2020-01-03T00:00:00Z",
        "end": "2020-01-03T23:59:59Z",
        "type": "public",
        "public": true,
        "country": "RU",
        "subdivisions": []
    }, {
        "id": "20200104_333d3690b1e4bc3aa5c1cd5a99a7fc3c",
        "name": "Fourth Day of the New Year",
        "date": "2020-01-04",
        "observed": "2020-01-04",
        "substitute": false,
        "start": "2020-01-04T00:00:00Z",
        "end": "2020-01-04T23:59:59Z",
        "type": "public",
        "public": true,
        "country": "RU",
        "subdivisions": []
    }, {
        "id": "20200105_717a23c56e33a9008444d1ca6ad0e145",
        "name": "Fifth Day of the New Year",
        "date": "2020-01-05",
        "observed": "2020-01-05",
        "substitute": false,
        "start": "2020-01-05T00:00:00Z",
        "end": "2020-01-05T23:59:59Z",
        "type": "public",
        "public": true,
        "country": "RU",
        "subdivisions": []
    }, {
        "id": "20200106_4f20f6efcb488fc3878b409a8e165ffd",
        "name": "Orthodox Christmas Eve",
        "date": "2020-01-06",
        "observed": "2020-01-06",
        "substitute": false,
        "start": "2020-01-06T00:00:00Z",
        "end": "2020-01-06T23:59:59Z",
        "type": "observance",
        "public": false,
        "country": "RU",
        "subdivisions": []
    }, {
        "id": "20200106_c32138ffd2792b4edfa9504f1b1a7073",
        "name": "Sixth Day of the New Year",
        "date": "2020-01-06",
        "observed": "2020-01-06",
        "substitute": false,
        "start": "2020-01-06T00:00:00Z",
        "end": "2020-01-06T23:59:59Z",
        "type": "public",
        "public": true,
        "country": "RU",
        "subdivisions": []
    }, {
        "id": "20200107_42db7d4dd73f3cecd6d55303f80f7620",
        "name": "Orthodox Christmas Day",
        "date": "2020-01-07",
        "observed": "2020-01-07",
        "substitute": false,
        "start": "2020-01-07T00:00:00Z",
        "end": "2020-01-07T23:59:59Z",
        "type": "public",
        "public": true,
        "country": "RU",
        "subdivisions": []
    }, {
        "id": "20200107_298b3c0461c936098f76e04d5a8dd526",
        "name": "Seventh Day of the New Year",
        "date": "2020-01-07",
        "observed": "2020-01-07",
        "substitute": false,
        "start": "2020-01-07T00:00:00Z",
        "end": "2020-01-07T23:59:59Z",
        "type": "observance",
        "public": false,
        "country": "RU",
        "subdivisions": []
    }, {
        "id": "20200108_eba025c78cb0dfbe5f008d68af5afd50",
        "name": "Eighth Day of the New Year",
        "date": "2020-01-08",
        "observed": "2020-01-08",
        "substitute": false,
        "start": "2020-01-08T00:00:00Z",
        "end": "2020-01-08T23:59:59Z",
        "type": "public",
        "public": true,
        "country": "RU",
        "subdivisions": []
    }, {
        "id": "20200112_d40eddaf5061458b91f35283f8db624f",
        "name": "Prosecutor General's Day",
        "date": "2020-01-12",
        "observed": "2020-01-12",
        "substitute": false,
        "start": "2020-01-12T00:00:00Z",
        "end": "2020-01-12T23:59:59Z",
        "type": "observance",
        "public": false,
        "country": "RU",
        "subdivisions": []
    }, {
        "id": "20200114_169af557378a1c1e23ecadd7142aede6",
        "name": "Old New Year's Day",
        "date": "2020-01-14",
        "observed": "2020-01-14",
        "substitute": false,
        "start": "2020-01-14T00:00:00Z",
        "end": "2020-01-14T23:59:59Z",
        "type": "observance",
        "public": false,
        "country": "RU",
        "subdivisions": []
    }, {
        "id": "20200125_720982e3a9faf9ce063b916e46e3c081",
        "name": "Tatiana Day",
        "date": "2020-01-25",
        "observed": "2020-01-25",
        "substitute": false,
        "start": "2020-01-25T00:00:00Z",
        "end": "2020-01-25T23:59:59Z",
        "type": "observance",
        "public": false,
        "country": "RU",
        "subdivisions": []
    }, {
        "id": "20200214_f258136104953a93d463a2a43cf389f7",
        "name": "Valentine's Day",
        "date": "2020-02-14",
        "observed": "2020-02-14",
        "substitute": false,
        "start": "2020-02-14T00:00:00Z",
        "end": "2020-02-14T23:59:59Z",
        "type": "observance",
        "public": false,
        "country": "RU",
        "subdivisions": []
    }, {
        "id": "20200215_63bfe0f69c57985614f4577a332b32c5",
        "name": "International Duties Memorial Day",
        "date": "2020-02-15",
        "observed": "2020-02-15",
        "substitute": false,
        "start": "2020-02-15T00:00:00Z",
        "end": "2020-02-15T23:59:59Z",
        "type": "observance",
        "public": false,
        "country": "RU",
        "subdivisions": []
    }, {
        "id": "20200223_2d445c0f1fb0affb3fca6033d78893fa",
        "name": "Defender of the Fatherland Day",
        "date": "2020-02-23",
        "observed": "2020-02-24",
        "substitute": true,
        "start": "2020-02-23T00:00:00Z",
        "end": "2020-02-23T23:59:59Z",
        "type": "public",
        "public": true,
        "country": "RU",
        "subdivisions": []
    }, {
        "id": "20200227_37bdd9fe45d606a1e0e9eccf57cffd0a",
        "name": "Special Operations Forces Day",
        "date": "2020-02-27",
        "observed": "2020-02-27",
        "substitute": false,
        "start": "2020-02-27T00:00:00Z",
        "end": "2020-02-27T23:59:59Z",
        "type": "observance",
        "public": false,
        "country": "RU",
        "subdivisions": []
    }, {
        "id": "20200303_a902fa4bf73543334a67a923db41db36",
        "name": "World Wildlife Day",
        "date": "2020-03-03",
        "observed": "2020-03-03",
        "substitute": false,
        "start": "2020-03-03T00:00:00Z",
        "end": "2020-03-03T23:59:59Z",
        "type": "observance",
        "public": false,
        "country": "RU",
        "subdivisions": []
    }, {
        "id": "20200308_ac7460e7720ea9ea461d14416045aa71",
        "name": "International Women's Day",
        "date": "2020-03-08",
        "observed": "2020-03-09",
        "substitute": true,
        "start": "2020-03-08T00:00:00Z",
        "end": "2020-03-08T23:59:59Z",
        "type": "public",
        "public": true,
        "country": "RU",
        "subdivisions": []
    }, {
        "id": "20200320_bd22074c8589efe8dd36fa6a3230c624",
        "name": "March Equinox",
        "date": "2020-03-20",
        "observed": "2020-03-20",
        "substitute": false,
        "start": "2020-03-20T00:00:00Z",
        "end": "2020-03-20T23:59:59Z",
        "type": "observance",
        "public": false,
        "country": "RU",
        "subdivisions": []
    }, {
        "id": "20200325_24397a0368ce87add294db756306c88f",
        "name": "Cultural Workers' Day",
        "date": "2020-03-25",
        "observed": "2020-03-25",
        "substitute": false,
        "start": "2020-03-25T00:00:00Z",
        "end": "2020-03-25T23:59:59Z",
        "type": "observance",
        "public": false,
        "country": "RU",
        "subdivisions": []
    }, {
        "id": "20200328_3fd9a3ae7a18656c3c49aa0e88a7c043",
        "name": "Public Holiday Due to COVID-19",
        "date": "2020-03-28",
        "observed": "2020-03-28",
        "substitute": false,
        "start": "2020-03-28T00:00:00Z",
        "end": "2020-03-28T23:59:59Z",
        "type": "public",
        "public": true,
        "country": "RU",
        "subdivisions": []
    }, {
        "id": "20200329_da84daf493310a7763f070123ad4fdfe",
        "name": "Public Holiday Due to COVID-19",
        "date": "2020-03-29",
        "observed": "2020-03-29",
        "substitute": false,
        "start": "2020-03-29T00:00:00Z",
        "end": "2020-03-29T23:59:59Z",
        "type": "public",
        "public": true,
        "country": "RU",
        "subdivisions": []
    }, {
        "id": "20200330_e2bffc45f0e8d2b9f0b89b6577c3177a",
        "name": "Public Holiday Due to COVID-19",
        "date": "2020-03-30",
        "observed": "2020-03-30",
        "substitute": false,
        "start": "2020-03-30T00:00:00Z",
        "end": "2020-03-30T23:59:59Z",
        "type": "public",
        "public": true,
        "country": "RU",
        "subdivisions": []
    }, {
        "id": "20200331_db438fa59f12d80b1269019345d08969",
        "name": "Public Holiday Due to COVID-19",
        "date": "2020-03-31",
        "observed": "2020-03-31",
        "substitute": false,
        "start": "2020-03-31T00:00:00Z",
        "end": "2020-03-31T23:59:59Z",
        "type": "public",
        "public": true,
        "country": "RU",
        "subdivisions": []
    }, {
        "id": "20200401_73238ad227a94fb3ea939bcef5e71a8a",
        "name": "Public Holiday Due to COVID-19",
        "date": "2020-04-01",
        "observed": "2020-04-01",
        "substitute": false,
        "start": "2020-04-01T00:00:00Z",
        "end": "2020-04-01T23:59:59Z",
        "type": "public",
        "public": true,
        "country": "RU",
        "subdivisions": []
    }, {
        "id": "20200402_3f6d0fef141125fff0cb7efa7be951fb",
        "name": "Public Holiday Due to COVID-19",
        "date": "2020-04-02",
        "observed": "2020-04-02",
        "substitute": false,
        "start": "2020-04-02T00:00:00Z",
        "end": "2020-04-02T23:59:59Z",
        "type": "public",
        "public": true,
        "country": "RU",
        "subdivisions": []
    }, {
        "id": "20200403_d9be856a14cb343aa9044817509e7ba5",
        "name": "Public Holiday Due to COVID-19",
        "date": "2020-04-03",
        "observed": "2020-04-03",
        "substitute": false,
        "start": "2020-04-03T00:00:00Z",
        "end": "2020-04-03T23:59:59Z",
        "type": "public",
        "public": true,
        "country": "RU",
        "subdivisions": []
    }, {
        "id": "20200404_95d7eac28c73bffc8fd46e4f00a53d1f",
        "name": "Public Holiday Due to COVID-19",
        "date": "2020-04-04",
        "observed": "2020-04-04",
        "substitute": false,
        "start": "2020-04-04T00:00:00Z",
        "end": "2020-04-04T23:59:59Z",
        "type": "public",
        "public": true,
        "country": "RU",
        "subdivisions": []
    }, {
        "id": "20200405_be607cd7b1e3397713a647731faa1995",
        "name": "Public Holiday Due to COVID-19",
        "date": "2020-04-05",
        "observed": "2020-04-05",
        "substitute": false,
        "start": "2020-04-05T00:00:00Z",
        "end": "2020-04-05T23:59:59Z",
        "type": "public",
        "public": true,
        "country": "RU",
        "subdivisions": []
    }, {
        "id": "20200406_6b46861c821c5241990950011fcc19ed",
        "name": "Public Holiday Due to COVID-19",
        "date": "2020-04-06",
        "observed": "2020-04-06",
        "substitute": false,
        "start": "2020-04-06T00:00:00Z",
        "end": "2020-04-06T23:59:59Z",
        "type": "public",
        "public": true,
        "country": "RU",
        "subdivisions": []
    }, {
        "id": "20200407_9022478035cdb3ca129322f026b9fd72",
        "name": "Public Holiday Due to COVID-19",
        "date": "2020-04-07",
        "observed": "2020-04-07",
        "substitute": false,
        "start": "2020-04-07T00:00:00Z",
        "end": "2020-04-07T23:59:59Z",
        "type": "public",
        "public": true,
        "country": "RU",
        "subdivisions": []
    }, {
        "id": "20200408_939a8628618fd69722ced1b5ae1975b9",
        "name": "Public Holiday Due to COVID-19",
        "date": "2020-04-08",
        "observed": "2020-04-08",
        "substitute": false,
        "start": "2020-04-08T00:00:00Z",
        "end": "2020-04-08T23:59:59Z",
        "type": "public",
        "public": true,
        "country": "RU",
        "subdivisions": []
    }, {
        "id": "20200409_c543bcd8cefe124bc90e6be388fc1521",
        "name": "Public Holiday Due to COVID-19",
        "date": "2020-04-09",
        "observed": "2020-04-09",
        "substitute": false,
        "start": "2020-04-09T00:00:00Z",
        "end": "2020-04-09T23:59:59Z",
        "type": "public",
        "public": true,
        "country": "RU",
        "subdivisions": []
    }, {
        "id": "20200410_e8f2aa5c53246aba75ce3e31083eebf3",
        "name": "Public Holiday Due to COVID-19",
        "date": "2020-04-10",
        "observed": "2020-04-10",
        "substitute": false,
        "start": "2020-04-10T00:00:00Z",
        "end": "2020-04-10T23:59:59Z",
        "type": "public",
        "public": true,
        "country": "RU",
        "subdivisions": []
    }, {
        "id": "20200411_5b9e7c2b56956e39df06b796df5896a5",
        "name": "Public Holiday Due to COVID-19",
        "date": "2020-04-11",
        "observed": "2020-04-11",
        "substitute": false,
        "start": "2020-04-11T00:00:00Z",
        "end": "2020-04-11T23:59:59Z",
        "type": "public",
        "public": true,
        "country": "RU",
        "subdivisions": []
    }, {
        "id": "20200412_47e894246e09d5655b16ad6f976d2b40",
        "name": "Easter",
        "date": "2020-04-12",
        "observed": "2020-04-12",
        "substitute": false,
        "start": "2020-04-12T00:00:00Z",
        "end": "2020-04-12T23:59:59Z",
        "type": "observance",
        "public": false,
        "country": "RU",
        "subdivisions": []
    }, {
        "id": "20200412_2aac76cf330a2192ddd854a3f431e0e2",
        "name": "Public Holiday Due to COVID-19",
        "date": "2020-04-12",
        "observed": "2020-04-12",
        "substitute": false,
        "start": "2020-04-12T00:00:00Z",
        "end": "2020-04-12T23:59:59Z",
        "type": "public",
        "public": true,
        "country": "RU",
        "subdivisions": []
    }, {
        "id": "20200413_82115a729ab3b1510084e195ad44a407",
        "name": "Public Holiday Due to COVID-19",
        "date": "2020-04-13",
        "observed": "2020-04-13",
        "substitute": false,
        "start": "2020-04-13T00:00:00Z",
        "end": "2020-04-13T23:59:59Z",
        "type": "public",
        "public": true,
        "country": "RU",
        "subdivisions": []
    }, {
        "id": "20200414_bf87d5b9a847a08251d5c5669bf2e4f9",
        "name": "Public Holiday Due to COVID-19",
        "date": "2020-04-14",
        "observed": "2020-04-14",
        "substitute": false,
        "start": "2020-04-14T00:00:00Z",
        "end": "2020-04-14T23:59:59Z",
        "type": "public",
        "public": true,
        "country": "RU",
        "subdivisions": []
    }, {
        "id": "20200415_88847c3b1ca1b59c4fba97cd56956355",
        "name": "Public Holiday Due to COVID-19",
        "date": "2020-04-15",
        "observed": "2020-04-15",
        "substitute": false,
        "start": "2020-04-15T00:00:00Z",
        "end": "2020-04-15T23:59:59Z",
        "type": "public",
        "public": true,
        "country": "RU",
        "subdivisions": []
    }, {
        "id": "20200416_333239c9675ee045076ef4f160b87a65",
        "name": "Public Holiday Due to COVID-19",
        "date": "2020-04-16",
        "observed": "2020-04-16",
        "substitute": false,
        "start": "2020-04-16T00:00:00Z",
        "end": "2020-04-16T23:59:59Z",
        "type": "public",
        "public": true,
        "country": "RU",
        "subdivisions": []
    }, {
        "id": "20200417_2994008c0d89fbb248e1286dbca2a56d",
        "name": "Public Holiday Due to COVID-19",
        "date": "2020-04-17",
        "observed": "2020-04-17",
        "substitute": false,
        "start": "2020-04-17T00:00:00Z",
        "end": "2020-04-17T23:59:59Z",
        "type": "public",
        "public": true,
        "country": "RU",
        "subdivisions": []
    }, {
        "id": "20200418_85abb1b87a0fc029e8fdaaaacc43190e",
        "name": "Public Holiday Due to COVID-19",
        "date": "2020-04-18",
        "observed": "2020-04-18",
        "substitute": false,
        "start": "2020-04-18T00:00:00Z",
        "end": "2020-04-18T23:59:59Z",
        "type": "public",
        "public": true,
        "country": "RU",
        "subdivisions": []
    }, {
        "id": "20200419_9f681163dea8ef31c4eb8fab838996fb",
        "name": "Public Holiday Due to COVID-19",
        "date": "2020-04-19",
        "observed": "2020-04-19",
        "substitute": false,
        "start": "2020-04-19T00:00:00Z",
        "end": "2020-04-19T23:59:59Z",
        "type": "public",
        "public": true,
        "country": "RU",
        "subdivisions": []
    }, {
        "id": "20200419_874febf4cead63f90401f3f57466b485",
        "name": "Orthodox Easter",
        "date": "2020-04-19",
        "observed": "2020-04-19",
        "substitute": false,
        "start": "2020-04-19T00:00:00Z",
        "end": "2020-04-19T23:59:59Z",
        "type": "observance",
        "public": false,
        "country": "RU",
        "subdivisions": []
    }, {
        "id": "20200420_691c66cf866022447381eda5bbb8ab2d",
        "name": "Public Holiday Due to COVID-19",
        "date": "2020-04-20",
        "observed": "2020-04-20",
        "substitute": false,
        "start": "2020-04-20T00:00:00Z",
        "end": "2020-04-20T23:59:59Z",
        "type": "public",
        "public": true,
        "country": "RU",
        "subdivisions": []
    }, {
        "id": "20200421_ad9692d21722045a4e6c143e678ad262",
        "name": "Public Holiday Due to COVID-19",
        "date": "2020-04-21",
        "observed": "2020-04-21",
        "substitute": false,
        "start": "2020-04-21T00:00:00Z",
        "end": "2020-04-21T23:59:59Z",
        "type": "public",
        "public": true,
        "country": "RU",
        "subdivisions": []
    }, {
        "id": "20200421_ed862b9eb6649b56b21fa466bf8bf32f",
        "name": "Local Self-Government Day",
        "date": "2020-04-21",
        "observed": "2020-04-21",
        "substitute": false,
        "start": "2020-04-21T00:00:00Z",
        "end": "2020-04-21T23:59:59Z",
        "type": "observance",
        "public": false,
        "country": "RU",
        "subdivisions": []
    }, {
        "id": "20200422_31c9ff456300742ee118b0bcb470d206",
        "name": "Public Holiday Due to COVID-19",
        "date": "2020-04-22",
        "observed": "2020-04-22",
        "substitute": false,
        "start": "2020-04-22T00:00:00Z",
        "end": "2020-04-22T23:59:59Z",
        "type": "public",
        "public": true,
        "country": "RU",
        "subdivisions": []
    }, {
        "id": "20200423_b55f37250d8dca9c2bf3886a6dd8d199",
        "name": "Public Holiday Due to COVID-19",
        "date": "2020-04-23",
        "observed": "2020-04-23",
        "substitute": false,
        "start": "2020-04-23T00:00:00Z",
        "end": "2020-04-23T23:59:59Z",
        "type": "public",
        "public": true,
        "country": "RU",
        "subdivisions": []
    }, {
        "id": "20200424_e5ff30f41a4dc0c63d5095addc1b5732",
        "name": "Public Holiday Due to COVID-19",
        "date": "2020-04-24",
        "observed": "2020-04-24",
        "substitute": false,
        "start": "2020-04-24T00:00:00Z",
        "end": "2020-04-24T23:59:59Z",
        "type": "public",
        "public": true,
        "country": "RU",
        "subdivisions": []
    }, {
        "id": "20200425_d7ce7bac3eb8f6a22db7e16b9503b235",
        "name": "Public Holiday Due to COVID-19",
        "date": "2020-04-25",
        "observed": "2020-04-25",
        "substitute": false,
        "start": "2020-04-25T00:00:00Z",
        "end": "2020-04-25T23:59:59Z",
        "type": "public",
        "public": true,
        "country": "RU",
        "subdivisions": []
    }, {
        "id": "20200426_dc17db56cf489ba4abf4af4fd8d054d9",
        "name": "Memorial Day of Radiation Accidents and Catastrophes",
        "date": "2020-04-26",
        "observed": "2020-04-26",
        "substitute": false,
        "start": "2020-04-26T00:00:00Z",
        "end": "2020-04-26T23:59:59Z",
        "type": "observance",
        "public": false,
        "country": "RU",
        "subdivisions": []
    }, {
        "id": "20200426_3c983f24f6ddd33d92415d593fdd78b8",
        "name": "Public Holiday Due to COVID-19",
        "date": "2020-04-26",
        "observed": "2020-04-26",
        "substitute": false,
        "start": "2020-04-26T00:00:00Z",
        "end": "2020-04-26T23:59:59Z",
        "type": "public",
        "public": true,
        "country": "RU",
        "subdivisions": []
    }, {
        "id": "20200427_dfcf62318799cbeb97c4495bbeb2ffae",
        "name": "Day of Russian Parliamentarism",
        "date": "2020-04-27",
        "observed": "2020-04-27",
        "substitute": false,
        "start": "2020-04-27T00:00:00Z",
        "end": "2020-04-27T23:59:59Z",
        "type": "observance",
        "public": false,
        "country": "RU",
        "subdivisions": []
    }, {
        "id": "20200427_a9071a336a8a5c9ed7dc2642baac69cc",
        "name": "Public Holiday Due to COVID-19",
        "date": "2020-04-27",
        "observed": "2020-04-27",
        "substitute": false,
        "start": "2020-04-27T00:00:00Z",
        "end": "2020-04-27T23:59:59Z",
        "type": "public",
        "public": true,
        "country": "RU",
        "subdivisions": []
    }, {
        "id": "20200428_4c637dcec01ce0a0260c1d6c88d420dd",
        "name": "Public Holiday Due to COVID-19",
        "date": "2020-04-28",
        "observed": "2020-04-28",
        "substitute": false,
        "start": "2020-04-28T00:00:00Z",
        "end": "2020-04-28T23:59:59Z",
        "type": "public",
        "public": true,
        "country": "RU",
        "subdivisions": []
    }, {
        "id": "20200429_e40dd889022d497d4843658bb0bb1fbd",
        "name": "Public Holiday Due to COVID-19",
        "date": "2020-04-29",
        "observed": "2020-04-29",
        "substitute": false,
        "start": "2020-04-29T00:00:00Z",
        "end": "2020-04-29T23:59:59Z",
        "type": "public",
        "public": true,
        "country": "RU",
        "subdivisions": []
    }, {
        "id": "20200430_edc958029716dd5f6aceae0c00f0e9e7",
        "name": "Public Holiday Due to COVID-19",
        "date": "2020-04-30",
        "observed": "2020-04-30",
        "substitute": false,
        "start": "2020-04-30T00:00:00Z",
        "end": "2020-04-30T23:59:59Z",
        "type": "public",
        "public": true,
        "country": "RU",
        "subdivisions": []
    }, {
        "id": "20200501_dc4640031ebe932e87fe432d8dd0a2f8",
        "name": "Spring and Labor Day",
        "date": "2020-05-01",
        "observed": "2020-05-01",
        "substitute": false,
        "start": "2020-05-01T00:00:00Z",
        "end": "2020-05-01T23:59:59Z",
        "type": "public",
        "public": true,
        "country": "RU",
        "subdivisions": []
    }, {
        "id": "20200504_735af0b0e329a11ac9e03f64ded813e8",
        "name": "Public Holiday (January 4th Substitute)",
        "date": "2020-05-04",
        "observed": "2020-05-04",
        "substitute": false,
        "start": "2020-05-04T00:00:00Z",
        "end": "2020-05-04T23:59:59Z",
        "type": "public",
        "public": true,
        "country": "RU",
        "subdivisions": []
    }, {
        "id": "20200505_925bb5edc1829ced0e2c6a20294083d7",
        "name": "Public Holiday (January 5th Substitute)",
        "date": "2020-05-05",
        "observed": "2020-05-05",
        "substitute": false,
        "start": "2020-05-05T00:00:00Z",
        "end": "2020-05-05T23:59:59Z",
        "type": "public",
        "public": true,
        "country": "RU",
        "subdivisions": []
    }, {
        "id": "20200509_7a8b583f7fb616c7916306ce4288b5f0",
        "name": "Victory Day",
        "date": "2020-05-09",
        "observed": "2020-05-11",
        "substitute": true,
        "start": "2020-05-09T00:00:00Z",
        "end": "2020-05-09T23:59:59Z",
        "type": "public",
        "public": true,
        "country": "RU",
        "subdivisions": []
    }, {
        "id": "20200606_939ef9e22054ceb67018adaf798ef22a",
        "name": "Day of the Russian Language",
        "date": "2020-06-06",
        "observed": "2020-06-06",
        "substitute": false,
        "start": "2020-06-06T00:00:00Z",
        "end": "2020-06-06T23:59:59Z",
        "type": "observance",
        "public": false,
        "country": "RU",
        "subdivisions": []
    }, {
        "id": "20200608_a0ed13ee4ea0e6cb39a75914f714d77f",
        "name": "Social Workers' Day",
        "date": "2020-06-08",
        "observed": "2020-06-08",
        "substitute": false,
        "start": "2020-06-08T00:00:00Z",
        "end": "2020-06-08T23:59:59Z",
        "type": "observance",
        "public": false,
        "country": "RU",
        "subdivisions": []
    }, {
        "id": "20200612_073768a2d2496e66598e701f554e2e45",
        "name": "Russia Day",
        "date": "2020-06-12",
        "observed": "2020-06-12",
        "substitute": false,
        "start": "2020-06-12T00:00:00Z",
        "end": "2020-06-12T23:59:59Z",
        "type": "public",
        "public": true,
        "country": "RU",
        "subdivisions": []
    }, {
        "id": "20200620_e1de4ad81ff989bfab15af5c49a6c445",
        "name": "June Solstice",
        "date": "2020-06-20",
        "observed": "2020-06-20",
        "substitute": false,
        "start": "2020-06-20T00:00:00Z",
        "end": "2020-06-20T23:59:59Z",
        "type": "observance",
        "public": false,
        "country": "RU",
        "subdivisions": []
    }, {
        "id": "20200630_2174c92b3e8a019cc4ffe8c46f471360",
        "name": "International Asteroid Day",
        "date": "2020-06-30",
        "observed": "2020-06-30",
        "substitute": false,
        "start": "2020-06-30T00:00:00Z",
        "end": "2020-06-30T23:59:59Z",
        "type": "observance",
        "public": false,
        "country": "RU",
        "subdivisions": []
    }, {
        "id": "20200718_71a1b4891dffbe87ecec96741e937e3f",
        "name": "Nelson Mandela International Day",
        "date": "2020-07-18",
        "observed": "2020-07-18",
        "substitute": false,
        "start": "2020-07-18T00:00:00Z",
        "end": "2020-07-18T23:59:59Z",
        "type": "observance",
        "public": false,
        "country": "RU",
        "subdivisions": []
    }, {
        "id": "20200726_65d6f26481c7fac6e6c9198d430608f5",
        "name": "Navy Day",
        "date": "2020-07-26",
        "observed": "2020-07-26",
        "substitute": false,
        "start": "2020-07-26T00:00:00Z",
        "end": "2020-07-26T23:59:59Z",
        "type": "observance",
        "public": false,
        "country": "RU",
        "subdivisions": []
    }, {
        "id": "20200802_3855e8927451b04a33a503ff336a9638",
        "name": "Railway Workers' Day",
        "date": "2020-08-02",
        "observed": "2020-08-02",
        "substitute": false,
        "start": "2020-08-02T00:00:00Z",
        "end": "2020-08-02T23:59:59Z",
        "type": "observance",
        "public": false,
        "country": "RU",
        "subdivisions": []
    }, {
        "id": "20200806_34d9619323eec7439ecb2756d2855aaf",
        "name": "Russian Railway Troops Day",
        "date": "2020-08-06",
        "observed": "2020-08-06",
        "substitute": false,
        "start": "2020-08-06T00:00:00Z",
        "end": "2020-08-06T23:59:59Z",
        "type": "observance",
        "public": false,
        "country": "RU",
        "subdivisions": []
    }, {
        "id": "20200808_ab849cdac5867c8798f9f6fc416c438e",
        "name": "Sports Day",
        "date": "2020-08-08",
        "observed": "2020-08-08",
        "substitute": false,
        "start": "2020-08-08T00:00:00Z",
        "end": "2020-08-08T23:59:59Z",
        "type": "observance",
        "public": false,
        "country": "RU",
        "subdivisions": []
    }, {
        "id": "20200812_3c842f2c3aac03cb4a0407a014dae7a1",
        "name": "Russian Air Force Day",
        "date": "2020-08-12",
        "observed": "2020-08-12",
        "substitute": false,
        "start": "2020-08-12T00:00:00Z",
        "end": "2020-08-12T23:59:59Z",
        "type": "observance",
        "public": false,
        "country": "RU",
        "subdivisions": []
    }, {
        "id": "20200822_8ce8532046b16017aa126d6db4de112f",
        "name": "National Flag Day",
        "date": "2020-08-22",
        "observed": "2020-08-22",
        "substitute": false,
        "start": "2020-08-22T00:00:00Z",
        "end": "2020-08-22T23:59:59Z",
        "type": "observance",
        "public": false,
        "country": "RU",
        "subdivisions": []
    }, {
        "id": "20200827_ac6b81fa2b76d5118eeaf3f4bd45a8a3",
        "name": "Film and Movies Day",
        "date": "2020-08-27",
        "observed": "2020-08-27",
        "substitute": false,
        "start": "2020-08-27T00:00:00Z",
        "end": "2020-08-27T23:59:59Z",
        "type": "observance",
        "public": false,
        "country": "RU",
        "subdivisions": []
    }, {
        "id": "20200922_d2c429a40f7512d696e2c038bce01c5f",
        "name": "September Equinox",
        "date": "2020-09-22",
        "observed": "2020-09-22",
        "substitute": false,
        "start": "2020-09-22T00:00:00Z",
        "end": "2020-09-22T23:59:59Z",
        "type": "observance",
        "public": false,
        "country": "RU",
        "subdivisions": []
    }, {
        "id": "20200929_7f88015207f525ec5e73c2a2058a1447",
        "name": "Day of Machine-Building industry workers",
        "date": "2020-09-29",
        "observed": "2020-09-29",
        "substitute": false,
        "start": "2020-09-29T00:00:00Z",
        "end": "2020-09-29T23:59:59Z",
        "type": "observance",
        "public": false,
        "country": "RU",
        "subdivisions": []
    }, {
        "id": "20201001_3e63fc228059501d800e43f702094786",
        "name": "International Day of Older Persons Russian Ground Forces Day",
        "date": "2020-10-01",
        "observed": "2020-10-01",
        "substitute": false,
        "start": "2020-10-01T00:00:00Z",
        "end": "2020-10-01T23:59:59Z",
        "type": "observance",
        "public": false,
        "country": "RU",
        "subdivisions": []
    }, {
        "id": "20201004_bbf1c8df5748f15dcb5bbf85bdf3f90a",
        "name": "Russian Aerospace Defence Forces Day",
        "date": "2020-10-04",
        "observed": "2020-10-04",
        "substitute": false,
        "start": "2020-10-04T00:00:00Z",
        "end": "2020-10-04T23:59:59Z",
        "type": "observance",
        "public": false,
        "country": "RU",
        "subdivisions": []
    }, {
        "id": "20201023_aa8b42f4577692091951523270ee0c4f",
        "name": "Day of Advertisement industry Workers",
        "date": "2020-10-23",
        "observed": "2020-10-23",
        "substitute": false,
        "start": "2020-10-23T00:00:00Z",
        "end": "2020-10-23T23:59:59Z",
        "type": "observance",
        "public": false,
        "country": "RU",
        "subdivisions": []
    }, {
        "id": "20201024_a9d911a29902944f6f6484aafbca2295",
        "name": "Day of Special Forces of the Armed Forces",
        "date": "2020-10-24",
        "observed": "2020-10-24",
        "substitute": false,
        "start": "2020-10-24T00:00:00Z",
        "end": "2020-10-24T23:59:59Z",
        "type": "observance",
        "public": false,
        "country": "RU",
        "subdivisions": []
    }, {
        "id": "20201025_3810c56dee99828fe8a7f8dca905cab1",
        "name": "Day of Customs Workers",
        "date": "2020-10-25",
        "observed": "2020-10-25",
        "substitute": false,
        "start": "2020-10-25T00:00:00Z",
        "end": "2020-10-25T23:59:59Z",
        "type": "observance",
        "public": false,
        "country": "RU",
        "subdivisions": []
    }, {
        "id": "20201029_ed0224a38d21aa57349bffca266c8a9d",
        "name": "Day of Security services of the MVD",
        "date": "2020-10-29",
        "observed": "2020-10-29",
        "substitute": false,
        "start": "2020-10-29T00:00:00Z",
        "end": "2020-10-29T23:59:59Z",
        "type": "observance",
        "public": false,
        "country": "RU",
        "subdivisions": []
    }, {
        "id": "20201030_fa685ca4679765a24e47d3f2bdb3b02f",
        "name": "Day of Remembrance of the Victims of Political Repressions",
        "date": "2020-10-30",
        "observed": "2020-10-30",
        "substitute": false,
        "start": "2020-10-30T00:00:00Z",
        "end": "2020-10-30T23:59:59Z",
        "type": "observance",
        "public": false,
        "country": "RU",
        "subdivisions": []
    }, {
        "id": "20201031_66ebfa709aedd6a7fc4be70ef0e6fe90",
        "name": "Day of the Detention Centers and Prisons Workers",
        "date": "2020-10-31",
        "observed": "2020-10-31",
        "substitute": false,
        "start": "2020-10-31T00:00:00Z",
        "end": "2020-10-31T23:59:59Z",
        "type": "observance",
        "public": false,
        "country": "RU",
        "subdivisions": []
    }, {
        "id": "20201104_c88ed70a21c59fd4098df79db390f238",
        "name": "Unity Day",
        "date": "2020-11-04",
        "observed": "2020-11-04",
        "substitute": false,
        "start": "2020-11-04T00:00:00Z",
        "end": "2020-11-04T23:59:59Z",
        "type": "public",
        "public": true,
        "country": "RU",
        "subdivisions": []
    }, {
        "id": "20201110_ea45e426a9d8f0f7fca98c4283ce50fb",
        "name": "Police and Internal Affairs Servicemen's Day",
        "date": "2020-11-10",
        "observed": "2020-11-10",
        "substitute": false,
        "start": "2020-11-10T00:00:00Z",
        "end": "2020-11-10T23:59:59Z",
        "type": "observance",
        "public": false,
        "country": "RU",
        "subdivisions": []
    }, {
        "id": "20201118_76704fb71db1391859a1a3907ae2c905",
        "name": "Day of the Missile Forces and Artillery",
        "date": "2020-11-18",
        "observed": "2020-11-18",
        "substitute": false,
        "start": "2020-11-18T00:00:00Z",
        "end": "2020-11-18T23:59:59Z",
        "type": "observance",
        "public": false,
        "country": "RU",
        "subdivisions": []
    }, {
        "id": "20201127_52d9828fff2374f593d32781d1991195",
        "name": "Naval Infantry Day",
        "date": "2020-11-27",
        "observed": "2020-11-27",
        "substitute": false,
        "start": "2020-11-27T00:00:00Z",
        "end": "2020-11-27T23:59:59Z",
        "type": "observance",
        "public": false,
        "country": "RU",
        "subdivisions": []
    }, {
        "id": "20201129_e2d3a9ad14678812dc68b55d4e54e790",
        "name": "Mother's Day",
        "date": "2020-11-29",
        "observed": "2020-11-29",
        "substitute": false,
        "start": "2020-11-29T00:00:00Z",
        "end": "2020-11-29T23:59:59Z",
        "type": "observance",
        "public": false,
        "country": "RU",
        "subdivisions": []
    }, {
        "id": "20201209_8e5d5710d15e6d3ca8aaeb608b6a741c",
        "name": "Fatherland's Heroes Day",
        "date": "2020-12-09",
        "observed": "2020-12-09",
        "substitute": false,
        "start": "2020-12-09T00:00:00Z",
        "end": "2020-12-09T23:59:59Z",
        "type": "observance",
        "public": false,
        "country": "RU",
        "subdivisions": []
    }, {
        "id": "20201217_41df0faec214d4ebf4829b53677cd740",
        "name": "Strategic Missile TroopsDay",
        "date": "2020-12-17",
        "observed": "2020-12-17",
        "substitute": false,
        "start": "2020-12-17T00:00:00Z",
        "end": "2020-12-17T23:59:59Z",
        "type": "observance",
        "public": false,
        "country": "RU",
        "subdivisions": []
    }, {
        "id": "20201221_60f7f98fc14d69e7f970e5c2b113a993",
        "name": "December Solstice",
        "date": "2020-12-21",
        "observed": "2020-12-21",
        "substitute": false,
        "start": "2020-12-21T00:00:00Z",
        "end": "2020-12-21T23:59:59Z",
        "type": "observance",
        "public": false,
        "country": "RU",
        "subdivisions": []
    }, {
        "id": "20201231_ab0fcdc353b797ee894de1c976e4d5a6",
        "name": "New Year's Eve",
        "date": "2020-12-31",
        "observed": "2020-12-31",
        "substitute": false,
        "start": "2020-12-31T00:00:00Z",
        "end": "2020-12-31T23:59:59Z",
        "type": "observance",
        "public": false,
        "country": "RU",
        "subdivisions": []
    }],
    "availableFilters": {
        "language": ["af", "am", "ar", "az", "be", "bg", "bn", "bs", "ca", "ceb", "co", "cs", "cy", "da", "de", "el", "en", "eo", "es", "et", "eu", "fa", "fi", "fr", "fy", "ga", "gd", "gl", "gu", "ha", "haw", "he", "hi", "hmn", "hr", "ht", "hu", "hy", "id", "ig", "is", "it", "ja", "jw", "ka", "kk", "km", "kn", "ko", "ku", "ky", "la", "lb", "lo", "lt", "lv", "mg", "mi", "mk", "ml", "mn", "mr", "ms", "mt", "my", "ne", "nl", "no", "ny", "or", "pa", "pl", "ps", "pt", "ro", "ru", "rw", "sd", "si", "sk", "sl", "sm", "sn", "so", "sq", "sr", "st", "su", "sv", "sw", "ta", "te", "tg", "th", "tk", "tl", "tr", "tt", "ug", "uk", "ur", "uz", "vi", "xh", "yi", "yo", "zh", "zh-TW", "zu"]
    }
}