{"status":200,"query":{"country":"YT","year":"2020"},"requestId":"bcc99a5e-73f7-4bcc-bb96-436d29271139","holidays":[{"id":"20200101_1449e5ddbe9787d2cac4743eb85391ee","name":"New Year's Day","date":"2020-01-01","observed":"2020-01-01","substitute":false,"start":"2020-01-01T00:00:00Z","end":"2020-01-01T23:59:59Z","type":"public","public":true,"country":"YT","subdivisions":[]},{"id":"20200320_5b1b026e07976031909bbc7bb0e5b391","name":"March Equinox","date":"2020-03-20","observed":"2020-03-20","substitute":false,"start":"2020-03-20T00:00:00Z","end":"2020-03-20T23:59:59Z","type":"observance","public":false,"country":"YT","subdivisions":[]},{"id":"20200321_4fbe88077e21cf06a264e0705c2b93c2","name":"Muhammad's Ascension to Heaven","date":"2020-03-21","observed":"2020-03-21","substitute":false,"start":"2020-03-21T00:00:00Z","end":"2020-03-21T23:59:59Z","type":"observance","public":false,"country":"YT","subdivisions":[]},{"id":"20200322_4fbe88077e21cf06a264e0705c2b93c2","name":"Muhammad's Ascension to Heaven","date":"2020-03-22","observed":"2020-03-22","substitute":false,"start":"2020-03-22T00:00:00Z","end":"2020-03-22T23:59:59Z","type":"observance","public":false,"country":"YT","subdivisions":[]},{"id":"20200412_8d49c9d90801ffb9725bcf4cfc40a375","name":"Easter","date":"2020-04-12","observed":"2020-04-12","substitute":false,"start":"2020-04-12T00:00:00Z","end":"2020-04-12T23:59:59Z","type":"observance","public":false,"country":"YT","subdivisions":[]},{"id":"20200413_a746419ec570c2d6ecb5424be1c4101e","name":"Easter Monday","date":"2020-04-13","observed":"2020-04-13","substitute":false,"start":"2020-04-13T00:00:00Z","end":"2020-04-13T23:59:59Z","type":"public","public":true,"country":"YT","subdivisions":[]},{"id":"20200427_06017831ca8a97977318c1103120b8f3","name":"Abolition of Slavery Day","date":"2020-04-27","observed":"2020-04-27","substitute":false,"start":"2020-04-27T00:00:00Z","end":"2020-04-27T23:59:59Z","type":"public","public":true,"country":"YT","subdivisions":[]},{"id":"20200501_077a28ca98813ae824fded9d20447612","name":"Labor Day","date":"2020-05-01","observed":"2020-05-01","substitute":false,"start":"2020-05-01T00:00:00Z","end":"2020-05-01T23:59:59Z","type":"public","public":true,"country":"YT","subdivisions":[]},{"id":"20200508_d4eb105fedae0e4aad37d04cb3f7ce7f","name":"Victory Day","date":"2020-05-08","observed":"2020-05-08","substitute":false,"start":"2020-05-08T00:00:00Z","end":"2020-05-08T23:59:59Z","type":"observance","public":false,"country":"YT","subdivisions":[]},{"id":"20200521_ed92c58fbd08c50b622939bc5213e835","name":"Feast of the Ascension of Jesus Christ","date":"2020-05-21","observed":"2020-05-21","substitute":false,"start":"2020-05-21T00:00:00Z","end":"2020-05-21T23:59:59Z","type":"observance","public":false,"country":"YT","subdivisions":[]},{"id":"20200523_b78579ae97d0e87416402d73c8a5cbb1","name":"Festival of Breaking the Fast","date":"2020-05-23","observed":"2020-05-23","substitute":false,"start":"2020-05-23T00:00:00Z","end":"2020-05-23T23:59:59Z","type":"observance","public":false,"country":"YT","subdivisions":[]},{"id":"20200524_b78579ae97d0e87416402d73c8a5cbb1","name":"Festival of Breaking the Fast","date":"2020-05-24","observed":"2020-05-24","substitute":false,"start":"2020-05-24T00:00:00Z","end":"2020-05-24T23:59:59Z","type":"observance","public":false,"country":"YT","subdivisions":[]},{"id":"20200601_37f84381264d2edff568181e4667d445","name":"Pentecost Monday","date":"2020-06-01","observed":"2020-06-01","substitute":false,"start":"2020-06-01T00:00:00Z","end":"2020-06-01T23:59:59Z","type":"observance","public":false,"country":"YT","subdivisions":[]},{"id":"20200620_bbabddd5aa92c31272c4ab4502829aaf","name":"June Solstice","date":"2020-06-20","observed":"2020-06-20","substitute":false,"start":"2020-06-20T00:00:00Z","end":"2020-06-20T23:59:59Z","type":"observance","public":false,"country":"YT","subdivisions":[]},{"id":"20200714_94377ea69193b54a8aaf1a98ebfea86f","name":"French National Day","date":"2020-07-14","observed":"2020-07-14","substitute":false,"start":"2020-07-14T00:00:00Z","end":"2020-07-14T23:59:59Z","type":"observance","public":false,"country":"YT","subdivisions":[]},{"id":"20200730_648d92b38ba0324b29265ce3392fb884","name":"Feast of the Sacrifice","date":"2020-07-30","observed":"2020-07-30","substitute":false,"start":"2020-07-30T00:00:00Z","end":"2020-07-30T23:59:59Z","type":"public","public":true,"country":"YT","subdivisions":[]},{"id":"20200731_648d92b38ba0324b29265ce3392fb884","name":"Feast of the Sacrifice","date":"2020-07-31","observed":"2020-07-31","substitute":false,"start":"2020-07-31T00:00:00Z","end":"2020-07-31T23:59:59Z","type":"public","public":true,"country":"YT","subdivisions":[]},{"id":"20200815_ad21e76ba2bbc4738fc0b650cf03759f","name":"Assumption of Mary","date":"2020-08-15","observed":"2020-08-15","substitute":false,"start":"2020-08-15T00:00:00Z","end":"2020-08-15T23:59:59Z","type":"observance","public":false,"country":"YT","subdivisions":[]},{"id":"20200922_df0a5700f14ff787a3f4e06cadba0bfd","name":"September Equinox","date":"2020-09-22","observed":"2020-09-22","substitute":false,"start":"2020-09-22T00:00:00Z","end":"2020-09-22T23:59:59Z","type":"observance","public":false,"country":"YT","subdivisions":[]},{"id":"20201028_1a3f8fd91e8c9469ee62a755e94b0e62","name":"Birth of the Prophet","date":"2020-10-28","observed":"2020-10-28","substitute":false,"start":"2020-10-28T00:00:00Z","end":"2020-10-28T23:59:59Z","type":"observance","public":false,"country":"YT","subdivisions":[]},{"id":"20201029_1a3f8fd91e8c9469ee62a755e94b0e62","name":"Birth of the Prophet","date":"2020-10-29","observed":"2020-10-29","substitute":false,"start":"2020-10-29T00:00:00Z","end":"2020-10-29T23:59:59Z","type":"observance","public":false,"country":"YT","subdivisions":[]},{"id":"20201101_5bec493cc4a409501b7b0e2f93b0a4ee","name":"Toussaint","date":"2020-11-01","observed":"2020-11-01","substitute":false,"start":"2020-11-01T00:00:00Z","end":"2020-11-01T23:59:59Z","type":"observance","public":false,"country":"YT","subdivisions":[]},{"id":"20201111_8efa07a5379944b6a2a5364fb2c86931","name":"Armistice Day","date":"2020-11-11","observed":"2020-11-11","substitute":false,"start":"2020-11-11T00:00:00Z","end":"2020-11-11T23:59:59Z","type":"observance","public":false,"country":"YT","subdivisions":[]},{"id":"20201221_4c32177880ef82a9a1dd9f95ddcd070a","name":"December Solstice","date":"2020-12-21","observed":"2020-12-21","substitute":false,"start":"2020-12-21T00:00:00Z","end":"2020-12-21T23:59:59Z","type":"observance","public":false,"country":"YT","subdivisions":[]},{"id":"20201224_5c6eab3ff079844cbdea10ed51421339","name":"Christmas Eve","date":"2020-12-24","observed":"2020-12-24","substitute":false,"start":"2020-12-24T00:00:00Z","end":"2020-12-24T23:59:59Z","type":"observance","public":false,"country":"YT","subdivisions":[]},{"id":"20201225_70e29263aa54c20f8ac181bc496084d5","name":"Christmas Day","date":"2020-12-25","observed":"2020-12-25","substitute":false,"start":"2020-12-25T00:00:00Z","end":"2020-12-25T23:59:59Z","type":"observance","public":false,"country":"YT","subdivisions":[]},{"id":"20201231_6da52b0f6a865151262fa9febb5b80a5","name":"New Year's Eve","date":"2020-12-31","observed":"2020-12-31","substitute":false,"start":"2020-12-31T00:00:00Z","end":"2020-12-31T23:59:59Z","type":"observance","public":false,"country":"YT","subdivisions":[]}],"availableFilters":{"language":["af","am","ar","az","be","bg","bn","bs","ca","ceb","co","cs","cy","da","de","el","en","eo","es","et","eu","fa","fi","fr","fy","ga","gd","gl","gu","ha","haw","he","hi","hmn","hr","ht","hu","hy","id","ig","is","it","ja","jw","ka","kk","km","kn","ko","ku","ky","la","lb","lo","lt","lv","mg","mi","mk","ml","mn","mr","ms","mt","my","ne","nl","no","ny","or","pa","pl","ps","pt","ro","ru","rw","sd","si","sk","sl","sm","sn","so","sq","sr","st","su","sv","sw","ta","te","tg","th","tk","tl","tr","tt","ug","uk","ur","uz","vi","xh","yi","yo","zh","zh-TW","zu"]}}